eprpy/__init__.py
eprpy/loader.py
eprpy/plotter.py
eprpy/processor.py
eprpy-0.9.0a4.dist-info/LICENSE
eprpy-0.9.0a4.dist-info/METADATA
eprpy-0.9.0a4.dist-info/WHEEL
eprpy-0.9.0a4.dist-info/top_level.txt
eprpy-0.9.0a4.dist-info/RECORD
