Metadata-Version: 2.2
Name: eprpy
Version: 0.9.0a4
Summary: A Python library for working with EPR spectroscopic data.
Home-page: https://github.com/davistdaniel/EPRpy
Author: Davis Thomas Daniel
Author-email: Davis Thomas Daniel <davisthomasdaniel@gmail.com>
Project-URL: Homepage, https://github.com/davistdaniel/EPRpy
Project-URL: Issues, https://github.com/davistdaniel/EPRpy/issues
Project-URL: Documentation, https://davistdaniel.github.io/EPRpy/
Project-URL: Repository, https://github.com/davistdaniel/EPRpy
Classifier: Development Status :: 3 - Alpha
Classifier: Programming Language :: Python :: 3
Classifier: Programming Language :: Python :: 3.9
Classifier: Programming Language :: Python :: 3.10
Classifier: Programming Language :: Python :: 3.11
Classifier: Programming Language :: Python :: 3.12
Classifier: Intended Audience :: Science/Research
Classifier: Topic :: Scientific/Engineering :: Physics
Classifier: Topic :: Scientific/Engineering :: Chemistry
Classifier: License :: OSI Approved :: MIT License
Requires-Python: >=3.9, <3.13.1
License-File: LICENSE
Requires-Dist: numpy
Requires-Dist: scipy
Requires-Dist: matplotlib
Dynamic: author
Dynamic: home-page
Dynamic: requires-python
